CoBaIR/__init__.py
CoBaIR/bayes_net.py
CoBaIR/configurator.py
CoBaIR/default_discretizer.py
CoBaIR/random_base_count.py
CoBaIR/visualization.py
tests/__init__.py
tests/test_add_context.py
tests/test_add_intention.py
tests/test_create_bayesNet.py
tests/test_delete_context.py
tests/test_delete_intention.py
tests/test_edit_context.py
tests/test_edit_intention.py
tests/test_infer.py
tests/test_load.py
tests/test_new_combined_influence.py
tests/test_remove_combined_influence.py
CoBaIR-4.0.3.dist-info/LICENSE
CoBaIR-4.0.3.dist-info/METADATA
CoBaIR-4.0.3.dist-info/WHEEL
CoBaIR-4.0.3.dist-info/top_level.txt
CoBaIR-4.0.3.dist-info/RECORD
