Metadata-Version: 2.1
Name: CoBaIR
Version: 4.0.3
Summary: CoBaIR is a Python library for Context Based Intention Recognition
Home-page: https://github.com/dfki-ric/CoBaIR
Author: Adrian Lubitz
Author-email: Adrian.Lubitz@dfki.de
License: BSD 3-Clause
Keywords: intention recognition context human machine interaction robot bayesian
Platform: UNKNOWN
Classifier: Development Status :: 3 - Alpha
Classifier: Environment :: X11 Applications :: Qt
Classifier: Intended Audience :: Science/Research
Classifier: Programming Language :: Python :: 3.8
Classifier: Topic :: Scientific/Engineering :: Artificial Intelligence
Classifier: Topic :: Utilities
Classifier: License :: OSI Approved :: BSD License
Requires-Python: >=3.8
License-File: LICENSE
Requires-Dist: pgmpy ==0.1.20
Requires-Dist: bnlearn ==0.7.10
Requires-Dist: pyyaml ==5.3.1
Requires-Dist: PyQt5 ==5.15.9
Requires-Dist: pyqtgraph ==0.13.3
